setup.py
pyanimenc/__init__.py
pyanimenc/chapter.py
pyanimenc/helpers.py
pyanimenc/pyanimenc.py
pyanimenc/script.py
pyanimenc.egg-info/PKG-INFO
pyanimenc.egg-info/SOURCES.txt
pyanimenc.egg-info/dependency_links.txt
pyanimenc.egg-info/entry_points.txt
pyanimenc.egg-info/requires.txt
pyanimenc.egg-info/top_level.txt
pyanimenc/glade/chapter.glade
pyanimenc/glade/encoders.glade
pyanimenc/glade/entry.glade
pyanimenc/glade/filters.glade
pyanimenc/glade/pyanimenc.glade
pyanimenc/glade/script.glade
pyanimenc/glade/track.glade