Metadata-Version: 1.1
Name: pyanimenc
Version: 0.1a1
Summary: Audio/Video Transcoding Frontend
Home-page: https://github.com/alucryd/pyanimenc
Author: Maxime Gauduin
Author-email: alucryd@gmail.com
License: GPL3
Keywords: audio video conversion
Platform: UNKNOWN
Classifier: Development Status :: 3 - Alpha
Classifier: Environment :: X11 Applications :: GTK
Classifier: Intended Audience :: End Users/Desktop
Classifier: License :: OSI Approved :: GNU General Public License v3 (GPLv3)
Classifier: Natural Language :: English
Classifier: Operating System :: POSIX :: Linux
Classifier: Programming Language :: Python :: 3
Classifier: Topic :: Multimedia :: Sound/Audio :: Conversion
Classifier: Topic :: Multimedia :: Video :: Conversion
